fragmentation_nx-0.2.1.dist-info/METADATA
fragmentation_nx-0.2.1.dist-info/WHEEL
nxx/__init__.py
nxx/nxx.cpython-38-x86_64-linux-gnu.so
fragmentation_nx-0.2.1.dist-info/RECORD
