Metadata-Version: 2.1
Name: fragmentation-nx
Version: 0.2.1
Classifier: Development Status :: 4 - Beta
Classifier: Intended Audience :: Science/Research
Classifier: Programming Language :: Python :: 3 :: Only
Classifier: Programming Language :: Python :: 3.8
Classifier: Programming Language :: Python :: 3.9
Classifier: Programming Language :: Python :: 3.10
Classifier: Programming Language :: Python :: 3.11
Classifier: Programming Language :: Rust
Classifier: Topic :: Scientific/Engineering
Requires-Dist: numpy
Requires-Dist: scipy
Requires-Dist: pytest; extra == 'test'
Requires-Dist: pytest-benchmark; extra == 'test'
Requires-Dist: networkx; extra == 'test'
Provides-Extra: test
Summary: Graph-theoretic fragment generation
Author-email: Harry Zhang <zhanghar@iu.edu>
Requires-Python: >=3.8
